grsba/__init__.py
grsba/grsba.py
grsba-2.6.2.dist-info/LICENSE.txt
grsba-2.6.2.dist-info/METADATA
grsba-2.6.2.dist-info/WHEEL
grsba-2.6.2.dist-info/top_level.txt
grsba-2.6.2.dist-info/RECORD
